ChangeLog.txt
LICENSE.txt
MANIFEST.in
README.txt
setup.py
signedimp/__init__.py
signedimp/bootstrap.py
signedimp/tools.py
signedimp/winres.py
signedimp.egg-info/PKG-INFO
signedimp.egg-info/SOURCES.txt
signedimp.egg-info/dependency_links.txt
signedimp.egg-info/top_level.txt
signedimp/crypto/__init__.py
signedimp/crypto/md5.py
signedimp/crypto/pss.py
signedimp/crypto/rsa.py
signedimp/crypto/sha1.py
signedimp/cryptobase/__init__.py
signedimp/cryptobase/md5.py
signedimp/cryptobase/pss.py
signedimp/cryptobase/rsa.py
signedimp/cryptobase/sha1.py
signedimp/tests/__init__.py
signedimp/tests/test_bootstrap.py
signedimp/tests/test_crypto.py
signedimp/tests/test_cryptobase.py
signedimp/tests/test_signedimp.py