Metadata-Version: 1.0
Name: signedimp
Version: 0.1.2
Summary: signed imports for verified loading of python modules
Home-page: http://github.com/cloudmatrix/signedimp/
Author: Ryan Kelly
Author-email: rfk@cloudmatrix.com.au
License: BSD
Keywords: code-signing verification import hooks
Platform: UNKNOWN
